<?xml version="1.0" encoding="utf-8"?>
<openerp>
    <data>

        <record id="apptype_redis" model="clouder.application.type">
            <field name="name">redis</field>
            <field name="system_user">redis</field>
        </record>
	<record id="apptype_redis_option_db_password" model="clouder.application.type.option">
            <field name="apptype_id" ref="apptype_redis"/>
            <field name="name">db_password</field>
            <field name="type">container</field>
            <field name="auto" eval="True"/>
        </record>

        <record id="image_redis" model="clouder.image">
            <field name="name">img_redis</field>
            <field name="type_id" ref="apptype_redis"/>
            <field name="current_version">3.2.1</field>
            <field name="parent_from">redis:3.2.1</field>
        </record>

	<record id ="image_redis_volume_data" model="clouder.image.volume">
	    <field name="image_id" ref="image_redis" />
	    <field name="name">/data</field>
	    <field name="user">redis</field>
	</record>

	<record id="image_redis_port_redis" model="clouder.image.port">
	    <field name="image_id" ref="image_redis"/>
    	    <field name="name">redis</field>
    	    <field name="localport">6379</field>
	</record>

        <record id="app_redis" model="clouder.application">
            <field name="name">Redis</field>
            <field name="code">redis</field>
            <field name="type_id" ref="apptype_redis"/>
            <field name="default_image_id" ref="image_redis"/>
        </record>
        <record id="app_redis_link_shinken" model="clouder.application.link">
            <field name="application_id" ref="app_redis"/>
            <field name="name" ref="clouder_template_shinken.app_shinken"/>
            <field name="auto" eval="True"/>
            <field name="container" eval="True"/>
        </record>

    </data>
</openerp>

